kora/__init__.py
kora/alt.py
kora/bio.py
kora/bokeh.py
kora/bs.py
kora/conda.py
kora/console.py
kora/data_table.py
kora/docker.py
kora/drive.py
kora/eda.py
kora/ffmpeg.py
kora/files.py
kora/fuzz.py
kora/gcloud.py
kora/hub.py
kora/json.py
kora/jupyter.py
kora/kaggle.py
kora/lda.py
kora/line.py
kora/mpl.py
kora/neo.py
kora/network.py
kora/ngrok.py
kora/nltk.py
kora/os.py
kora/output.py
kora/pd.py
kora/record.py
kora/reload.py
kora/selenium.py
kora/speech.py
kora/streamlit.py
kora/string.py
kora/thpronun.py
kora/translate.py
kora/tree.py
kora/trimesh.py
kora/xattr.py
kora/xml.py
kora/ai/__init__.py
kora/ai/colorizer.py
kora/ai/en2th.py
kora/ai/image2mesh.py
kora/ai/th2en.py
kora/datasets/BEST.py
kora/datasets/LOTUS.py
kora/datasets/ORCHID.py
kora/datasets/PPWC.py
kora/datasets/SCBMT.py
kora/datasets/TSync1.py
kora/datasets/TSync2.py
kora/datasets/TTC.py
kora/datasets/__init__.py
kora/install/__init__.py
kora/install/bat.py
kora/install/bazel.py
kora/install/blender.py
kora/install/deno.py
kora/install/es7.py
kora/install/fd.py
kora/install/influxdb.py
kora/install/kaldi.py
kora/install/lit_nlp.py
kora/install/manim.py
kora/install/mongodb.py
kora/install/mssql.py
kora/install/mysql8.py
kora/install/orca.py
kora/install/pg10.py
kora/install/pg13.py
kora/install/py38.py
kora/install/rdkit.py
kora/install/rg.py
kora/install/rust.py
kora/install/speech.py
kora/install/talib.py
kora/install/tldr.py
kora/install/yarn.py
kora/s/__init__.py
kora/s/activations.py
kora/s/backend.py
kora/s/callbacks.py
kora/s/initializers.py
kora/s/layers.py
kora/s/losses.py
kora/s/metrics.py
kora/s/models.py
kora/s/optimizers.py
kora/s/regularizers.py
kora/update/__init__.py
kora/update/sqlite.py
kora/update/tornado.py
kora/viz/__init__.py
kora/viz/bar_chart_race.py
kora/viz/chem.py
kora/viz/venn.py
kora/viz/wordcloud.py
kora-0.9.20.dist-info/LICENSE
kora-0.9.20.dist-info/METADATA
kora-0.9.20.dist-info/WHEEL
kora-0.9.20.dist-info/top_level.txt
kora-0.9.20.dist-info/RECORD
