Metadata-Version: 2.1
Name: kora
Version: 0.9.20
Summary: Convenient tools for Colab
Home-page: https://github.com/korakot/kora
Author: Korakot Chaovavanich
Author-email: korakot@gmail.com
License: UNKNOWN
Platform: UNKNOWN
Classifier: Programming Language :: Python :: 3
Classifier: License :: OSI Approved :: MIT License
Classifier: Operating System :: OS Independent
Requires-Python: >=3.6
